{"config":{"output_file":null,"full_docs":false,"pub_only":false,"reachable_only":false,"distro_crate":false,"signatures":false,"borrow_data":false},"version":"0.18.2","compilation":{"directory":[47,104,111,109,101,47,97,114,101,101,98,47,81,117,97,114,116,101,114,45,48,50,47,50,50,68,101,99,50,48,49,57],"program":"/home/areeb/.rustup/toolchains/stable-x86_64-unknown-linux-gnu/bin/rls","arguments":[],"output":[47,104,111,109,101,47,97,114,101,101,98,47,81,117,97,114,116,101,114,45,48,50,47,50,50,68,101,99,50,48,49,57,47,116,97,114,103,101,116,47,114,108,115,47,100,101,98,117,103,47,100,101,112,115,47,108,105,98,68,101,99,50,50,45,52,55,51,54,98,52,56,50,98,53,99,54,50,53,50,97,46,114,109,101,116,97]},"prelude":{"crate_id":{"name":"Dec22","disambiguator":[13988547391586761994,15313085418295184712]},"crate_root":"src","external_crates":[{"file_name":"/home/areeb/Quarter-02/22Dec2019/src/main.rs","num":1,"id":{"name":"std","disambiguator":[1137707474377317163,881293823083572693]}},{"file_name":"/home/areeb/Quarter-02/22Dec2019/src/main.rs","num":2,"id":{"name":"core","disambiguator":[16254816028303588237,6669189139375923666]}},{"file_name":"/home/areeb/Quarter-02/22Dec2019/src/main.rs","num":3,"id":{"name":"compiler_builtins","disambiguator":[7111806954579578569,2199841390691958019]}},{"file_name":"/home/areeb/Quarter-02/22Dec2019/src/main.rs","num":4,"id":{"name":"rustc_std_workspace_core","disambiguator":[6021837240640825503,11520007856923678909]}},{"file_name":"/home/areeb/Quarter-02/22Dec2019/src/main.rs","num":5,"id":{"name":"alloc","disambiguator":[12444724012878050064,2416873571855687959]}},{"file_name":"/home/areeb/Quarter-02/22Dec2019/src/main.rs","num":6,"id":{"name":"libc","disambiguator":[6979589238717360547,5382701582921578244]}},{"file_name":"/home/areeb/Quarter-02/22Dec2019/src/main.rs","num":7,"id":{"name":"unwind","disambiguator":[14383072016947483551,11019396538837452451]}},{"file_name":"/home/areeb/Quarter-02/22Dec2019/src/main.rs","num":8,"id":{"name":"rustc_demangle","disambiguator":[15664728184530138178,15668582881963515515]}},{"file_name":"/home/areeb/Quarter-02/22Dec2019/src/main.rs","num":9,"id":{"name":"backtrace_sys","disambiguator":[16547370833325286379,14798728708606514427]}},{"file_name":"/home/areeb/Quarter-02/22Dec2019/src/main.rs","num":10,"id":{"name":"panic_unwind","disambiguator":[3405404226459150258,2890948387317429027]}},{"file_name":"/home/areeb/Quarter-02/22Dec2019/src/main.rs","num":11,"id":{"name":"test","disambiguator":[16114603091502619109,14965242909132299906]}},{"file_name":"/home/areeb/Quarter-02/22Dec2019/src/main.rs","num":12,"id":{"name":"getopts","disambiguator":[16821432112065150025,13941231203349084683]}},{"file_name":"/home/areeb/Quarter-02/22Dec2019/src/main.rs","num":13,"id":{"name":"term","disambiguator":[4024357210454325105,15654644789240441761]}}],"span":{"file_name":[115,114,99,47,109,97,105,110,46,114,115],"byte_start":0,"byte_end":1332,"line_start":1,"line_end":68,"column_start":1,"column_end":2}},"imports":[{"kind":"Use","ref_id":{"krate":1,"index":500},"span":{"file_name":[115,114,99,47,109,97,105,110,46,114,115],"byte_start":9,"byte_end":15,"line_start":1,"line_end":1,"column_start":10,"column_end":16},"alias_span":null,"name":"thread","value":"","parent":{"krate":0,"index":0}},{"kind":"Use","ref_id":{"krate":2,"index":44730},"span":{"file_name":[115,114,99,47,109,97,105,110,46,114,115],"byte_start":32,"byte_end":40,"line_start":2,"line_end":2,"column_start":16,"column_end":24},"alias_span":null,"name":"Duration","value":"","parent":{"krate":0,"index":0}}],"defs":[{"kind":"Mod","id":{"krate":0,"index":0},"span":{"file_name":[115,114,99,47,109,97,105,110,46,114,115],"byte_start":0,"byte_end":1332,"line_start":1,"line_end":68,"column_start":1,"column_end":2},"name":"","qualname":"::","value":"src/main.rs","parent":null,"children":[{"krate":0,"index":2},{"krate":0,"index":4},{"krate":0,"index":6},{"krate":0,"index":8},{"krate":0,"index":10},{"krate":0,"index":12},{"krate":0,"index":18},{"krate":0,"index":20},{"krate":0,"index":22}],"decl_id":null,"docs":"","sig":null,"attributes":[]},{"kind":"Struct","id":{"krate":0,"index":10},"span":{"file_name":[115,114,99,47,109,97,105,110,46,114,115],"byte_start":50,"byte_end":56,"line_start":4,"line_end":4,"column_start":8,"column_end":14},"name":"Cacher","qualname":"::Cacher","value":"Cacher { calculation, value }","parent":null,"children":[{"krate":0,"index":21},{"krate":0,"index":23}],"decl_id":null,"docs":"","sig":null,"attributes":[]},{"kind":"Field","id":{"krate":0,"index":21},"span":{"file_name":[115,114,99,47,109,97,105,110,46,114,115],"byte_start":95,"byte_end":106,"line_start":7,"line_end":7,"column_start":5,"column_end":16},"name":"calculation","qualname":"::Cacher::calculation","value":"T","parent":{"krate":0,"index":10},"children":[],"decl_id":null,"docs":"","sig":null,"attributes":[]},{"kind":"Field","id":{"krate":0,"index":23},"span":{"file_name":[115,114,99,47,109,97,105,110,46,114,115],"byte_start":115,"byte_end":120,"line_start":8,"line_end":8,"column_start":5,"column_end":10},"name":"value","qualname":"::Cacher::value","value":"std::option::Option<u32>","parent":{"krate":0,"index":10},"children":[],"decl_id":null,"docs":"","sig":null,"attributes":[]},{"kind":"Type","id":{"krate":0,"index":19},"span":{"file_name":[115,114,99,47,109,97,105,110,46,114,115],"byte_start":58,"byte_end":59,"line_start":4,"line_end":4,"column_start":16,"column_end":17},"name":"T","qualname":"::Cacher::T$21","value":"","parent":null,"children":[],"decl_id":null,"docs":"","sig":null,"attributes":[]},{"kind":"Type","id":{"krate":0,"index":25},"span":{"file_name":[115,114,99,47,109,97,105,110,46,114,115],"byte_start":144,"byte_end":145,"line_start":12,"line_end":12,"column_start":7,"column_end":8},"name":"T","qualname":"::T$40","value":"","parent":null,"children":[],"decl_id":null,"docs":"","sig":null,"attributes":[]},{"kind":"Local","id":{"krate":0,"index":4294967237},"span":{"file_name":[115,114,99,47,109,97,105,110,46,114,115],"byte_start":202,"byte_end":213,"line_start":14,"line_end":14,"column_start":16,"column_end":27},"name":"calculation","qualname":"<Cacher<T>>::new::calculation","value":"T","parent":null,"children":[],"decl_id":null,"docs":"","sig":null,"attributes":[]},{"kind":"Method","id":{"krate":0,"index":14},"span":{"file_name":[115,114,99,47,109,97,105,110,46,114,115],"byte_start":198,"byte_end":201,"line_start":14,"line_end":14,"column_start":12,"column_end":15},"name":"new","qualname":"<Cacher<T>>::new","value":"fn (calculation: T) -> Self","parent":null,"children":[],"decl_id":null,"docs":"","sig":null,"attributes":[]},{"kind":"Local","id":{"krate":0,"index":4294967222},"span":{"file_name":[115,114,99,47,109,97,105,110,46,114,115],"byte_start":354,"byte_end":358,"line_start":21,"line_end":21,"column_start":27,"column_end":31},"name":"self","qualname":"<Cacher<T>>::the_value::self","value":"&mut Cacher<T>","parent":null,"children":[],"decl_id":null,"docs":"","sig":null,"attributes":[]},{"kind":"Local","id":{"krate":0,"index":4294967218},"span":{"file_name":[115,114,99,47,109,97,105,110,46,114,115],"byte_start":360,"byte_end":361,"line_start":21,"line_end":21,"column_start":33,"column_end":34},"name":"x","qualname":"<Cacher<T>>::the_value::x","value":"u32","parent":null,"children":[],"decl_id":null,"docs":"","sig":null,"attributes":[]},{"kind":"Method","id":{"krate":0,"index":16},"span":{"file_name":[115,114,99,47,109,97,105,110,46,114,115],"byte_start":339,"byte_end":348,"line_start":21,"line_end":21,"column_start":12,"column_end":21},"name":"the_value","qualname":"<Cacher<T>>::the_value","value":"fn (&mut self, x: u32) -> u32","parent":null,"children":[],"decl_id":null,"docs":"","sig":null,"attributes":[]},{"kind":"Local","id":{"krate":0,"index":4294967207},"span":{"file_name":[115,114,99,47,109,97,105,110,46,114,115],"byte_start":427,"byte_end":428,"line_start":23,"line_end":23,"column_start":21,"column_end":22},"name":"v","qualname":"v$88","value":"u32","parent":null,"children":[],"decl_id":null,"docs":"","sig":null,"attributes":[]},{"kind":"Local","id":{"krate":0,"index":4294967201},"span":{"file_name":[115,114,99,47,109,97,105,110,46,114,115],"byte_start":485,"byte_end":486,"line_start":25,"line_end":25,"column_start":24,"column_end":25},"name":"v","qualname":"v$94","value":"u32","parent":null,"children":[],"decl_id":null,"docs":"","sig":null,"attributes":[]},{"kind":"Local","id":{"krate":0,"index":4294967179},"span":{"file_name":[115,114,99,47,109,97,105,110,46,114,115],"byte_start":648,"byte_end":657,"line_start":39,"line_end":39,"column_start":25,"column_end":34},"name":"intensity","qualname":"::generate_workoutplan::intensity","value":"u32","parent":null,"children":[],"decl_id":null,"docs":"","sig":null,"attributes":[]},{"kind":"Local","id":{"krate":0,"index":4294967175},"span":{"file_name":[115,114,99,47,109,97,105,110,46,114,115],"byte_start":664,"byte_end":674,"line_start":39,"line_end":39,"column_start":41,"column_end":51},"name":"random_num","qualname":"::generate_workoutplan::random_num","value":"u32","parent":null,"children":[],"decl_id":null,"docs":"","sig":null,"attributes":[]},{"kind":"Function","id":{"krate":0,"index":18},"span":{"file_name":[115,114,99,47,109,97,105,110,46,114,115],"byte_start":627,"byte_end":647,"line_start":39,"line_end":39,"column_start":4,"column_end":24},"name":"generate_workoutplan","qualname":"::generate_workoutplan","value":"fn (intensity: u32, random_num: u32) -> ()","parent":null,"children":[],"decl_id":null,"docs":"","sig":null,"attributes":[]},{"kind":"Local","id":{"krate":0,"index":4294967169},"span":{"file_name":[115,114,99,47,109,97,105,110,46,114,115],"byte_start":693,"byte_end":714,"line_start":40,"line_end":40,"column_start":12,"column_end":33},"name":"expensive_calculation","qualname":"expensive_calculation$126","value":"Cacher<[closure@src/main.rs:40:48: 44:6]>","parent":null,"children":[],"decl_id":null,"docs":"","sig":null,"attributes":[]},{"kind":"Local","id":{"krate":0,"index":4294967164},"span":{"file_name":[115,114,99,47,109,97,105,110,46,114,115],"byte_start":730,"byte_end":733,"line_start":40,"line_end":40,"column_start":49,"column_end":52},"name":"num","qualname":"$146::num","value":"u32","parent":null,"children":[],"decl_id":null,"docs":"","sig":null,"attributes":[]},{"kind":"Function","id":{"krate":0,"index":20},"span":{"file_name":[115,114,99,47,109,97,105,110,46,114,115],"byte_start":1289,"byte_end":1293,"line_start":66,"line_end":66,"column_start":4,"column_end":8},"name":"main","qualname":"::main","value":"fn () -> ()","parent":null,"children":[],"decl_id":null,"docs":"","sig":null,"attributes":[{"value":"allow(dead_code)","span":{"file_name":[115,114,99,47,109,97,105,110,46,114,115],"byte_start":0,"byte_end":0,"line_start":1,"line_end":1,"column_start":1,"column_end":1}}]}],"impls":[{"id":0,"kind":"Inherent","span":{"file_name":[115,114,99,47,109,97,105,110,46,114,115],"byte_start":147,"byte_end":153,"line_start":12,"line_end":12,"column_start":10,"column_end":16},"value":"","parent":null,"children":[{"krate":0,"index":14},{"krate":0,"index":16}],"docs":"","sig":null,"attributes":[]}],"refs":[{"kind":"Mod","span":{"file_name":[115,114,99,47,109,97,105,110,46,114,115],"byte_start":4,"byte_end":7,"line_start":1,"line_end":1,"column_start":5,"column_end":8},"ref_id":{"krate":1,"index":0}},{"kind":"Mod","span":{"file_name":[115,114,99,47,109,97,105,110,46,114,115],"byte_start":21,"byte_end":24,"line_start":2,"line_end":2,"column_start":5,"column_end":8},"ref_id":{"krate":1,"index":0}},{"kind":"Mod","span":{"file_name":[115,114,99,47,109,97,105,110,46,114,115],"byte_start":26,"byte_end":30,"line_start":2,"line_end":2,"column_start":10,"column_end":14},"ref_id":{"krate":1,"index":8040}},{"kind":"Type","span":{"file_name":[115,114,99,47,109,97,105,110,46,114,115],"byte_start":108,"byte_end":109,"line_start":7,"line_end":7,"column_start":18,"column_end":19},"ref_id":{"krate":0,"index":19}},{"kind":"Type","span":{"file_name":[115,114,99,47,109,97,105,110,46,114,115],"byte_start":122,"byte_end":128,"line_start":8,"line_end":8,"column_start":12,"column_end":18},"ref_id":{"krate":2,"index":42482}},{"kind":"Type","span":{"file_name":[115,114,99,47,109,97,105,110,46,114,115],"byte_start":75,"byte_end":77,"line_start":5,"line_end":5,"column_start":14,"column_end":16},"ref_id":{"krate":2,"index":1998}},{"kind":"Type","span":{"file_name":[115,114,99,47,109,97,105,110,46,114,115],"byte_start":72,"byte_end":73,"line_start":5,"line_end":5,"column_start":11,"column_end":12},"ref_id":{"krate":0,"index":19}},{"kind":"Type","span":{"file_name":[115,114,99,47,109,97,105,110,46,114,115],"byte_start":147,"byte_end":153,"line_start":12,"line_end":12,"column_start":10,"column_end":16},"ref_id":{"krate":0,"index":10}},{"kind":"Type","span":{"file_name":[115,114,99,47,109,97,105,110,46,114,115],"byte_start":155,"byte_end":156,"line_start":12,"line_end":12,"column_start":18,"column_end":19},"ref_id":{"krate":0,"index":25}},{"kind":"Type","span":{"file_name":[115,114,99,47,109,97,105,110,46,114,115],"byte_start":171,"byte_end":173,"line_start":13,"line_end":13,"column_start":14,"column_end":16},"ref_id":{"krate":2,"index":1998}},{"kind":"Type","span":{"file_name":[115,114,99,47,109,97,105,110,46,114,115],"byte_start":168,"byte_end":169,"line_start":13,"line_end":13,"column_start":11,"column_end":12},"ref_id":{"krate":0,"index":25}},{"kind":"Type","span":{"file_name":[115,114,99,47,109,97,105,110,46,114,115],"byte_start":214,"byte_end":215,"line_start":14,"line_end":14,"column_start":28,"column_end":29},"ref_id":{"krate":0,"index":25}},{"kind":"Type","span":{"file_name":[115,114,99,47,109,97,105,110,46,114,115],"byte_start":239,"byte_end":243,"line_start":15,"line_end":15,"column_start":13,"column_end":17},"ref_id":{"krate":0,"index":10}},{"kind":"Variable","span":{"file_name":[115,114,99,47,109,97,105,110,46,114,115],"byte_start":262,"byte_end":273,"line_start":16,"line_end":16,"column_start":17,"column_end":28},"ref_id":{"krate":0,"index":21}},{"kind":"Variable","span":{"file_name":[115,114,99,47,109,97,105,110,46,114,115],"byte_start":262,"byte_end":273,"line_start":16,"line_end":16,"column_start":17,"column_end":28},"ref_id":{"krate":0,"index":4294967237}},{"kind":"Variable","span":{"file_name":[115,114,99,47,109,97,105,110,46,114,115],"byte_start":291,"byte_end":296,"line_start":17,"line_end":17,"column_start":17,"column_end":22},"ref_id":{"krate":0,"index":23}},{"kind":"Variable","span":{"file_name":[115,114,99,47,109,97,105,110,46,114,115],"byte_start":297,"byte_end":301,"line_start":17,"line_end":17,"column_start":23,"column_end":27},"ref_id":{"krate":2,"index":22887}},{"kind":"Variable","span":{"file_name":[115,114,99,47,109,97,105,110,46,114,115],"byte_start":394,"byte_end":398,"line_start":22,"line_end":22,"column_start":18,"column_end":22},"ref_id":{"krate":0,"index":4294967222}},{"kind":"Variable","span":{"file_name":[115,114,99,47,109,97,105,110,46,114,115],"byte_start":399,"byte_end":404,"line_start":22,"line_end":22,"column_start":23,"column_end":28},"ref_id":{"krate":0,"index":23}},{"kind":"Variable","span":{"file_name":[115,114,99,47,109,97,105,110,46,114,115],"byte_start":422,"byte_end":426,"line_start":23,"line_end":23,"column_start":16,"column_end":20},"ref_id":{"krate":2,"index":22891}},{"kind":"Variable","span":{"file_name":[115,114,99,47,109,97,105,110,46,114,115],"byte_start":422,"byte_end":426,"line_start":23,"line_end":23,"column_start":16,"column_end":20},"ref_id":{"krate":2,"index":22891}},{"kind":"Variable","span":{"file_name":[115,114,99,47,109,97,105,110,46,114,115],"byte_start":433,"byte_end":434,"line_start":23,"line_end":23,"column_start":27,"column_end":28},"ref_id":{"krate":0,"index":4294967207}},{"kind":"Variable","span":{"file_name":[115,114,99,47,109,97,105,110,46,114,115],"byte_start":451,"byte_end":455,"line_start":24,"line_end":24,"column_start":16,"column_end":20},"ref_id":{"krate":2,"index":22887}},{"kind":"Variable","span":{"file_name":[115,114,99,47,109,97,105,110,46,114,115],"byte_start":490,"byte_end":494,"line_start":25,"line_end":25,"column_start":29,"column_end":33},"ref_id":{"krate":0,"index":4294967222}},{"kind":"Variable","span":{"file_name":[115,114,99,47,109,97,105,110,46,114,115],"byte_start":495,"byte_end":506,"line_start":25,"line_end":25,"column_start":34,"column_end":45},"ref_id":{"krate":0,"index":21}},{"kind":"Variable","span":{"file_name":[115,114,99,47,109,97,105,110,46,114,115],"byte_start":509,"byte_end":510,"line_start":25,"line_end":25,"column_start":48,"column_end":49},"ref_id":{"krate":0,"index":4294967218}},{"kind":"Variable","span":{"file_name":[115,114,99,47,109,97,105,110,46,114,115],"byte_start":532,"byte_end":536,"line_start":26,"line_end":26,"column_start":20,"column_end":24},"ref_id":{"krate":0,"index":4294967222}},{"kind":"Variable","span":{"file_name":[115,114,99,47,109,97,105,110,46,114,115],"byte_start":537,"byte_end":542,"line_start":26,"line_end":26,"column_start":25,"column_end":30},"ref_id":{"krate":0,"index":23}},{"kind":"Variable","span":{"file_name":[115,114,99,47,109,97,105,110,46,114,115],"byte_start":545,"byte_end":549,"line_start":26,"line_end":26,"column_start":33,"column_end":37},"ref_id":{"krate":2,"index":22891}},{"kind":"Variable","span":{"file_name":[115,114,99,47,109,97,105,110,46,114,115],"byte_start":550,"byte_end":551,"line_start":26,"line_end":26,"column_start":38,"column_end":39},"ref_id":{"krate":0,"index":4294967201}},{"kind":"Variable","span":{"file_name":[115,114,99,47,109,97,105,110,46,114,115],"byte_start":573,"byte_end":574,"line_start":27,"line_end":27,"column_start":20,"column_end":21},"ref_id":{"krate":0,"index":4294967201}},{"kind":"Function","span":{"file_name":[115,114,99,47,109,97,105,110,46,114,115],"byte_start":725,"byte_end":728,"line_start":40,"line_end":40,"column_start":44,"column_end":47},"ref_id":{"krate":0,"index":14}},{"kind":"Type","span":{"file_name":[115,114,99,47,109,97,105,110,46,114,115],"byte_start":717,"byte_end":723,"line_start":40,"line_end":40,"column_start":36,"column_end":42},"ref_id":{"krate":0,"index":10}},{"kind":"Function","span":{"file_name":[115,114,99,47,109,97,105,110,46,114,115],"byte_start":796,"byte_end":801,"line_start":42,"line_end":42,"column_start":17,"column_end":22},"ref_id":{"krate":1,"index":698}},{"kind":"Mod","span":{"file_name":[115,114,99,47,109,97,105,110,46,114,115],"byte_start":788,"byte_end":794,"line_start":42,"line_end":42,"column_start":9,"column_end":15},"ref_id":{"krate":1,"index":500}},{"kind":"Function","span":{"file_name":[115,114,99,47,109,97,105,110,46,114,115],"byte_start":812,"byte_end":821,"line_start":42,"line_end":42,"column_start":33,"column_end":42},"ref_id":{"krate":2,"index":47082}},{"kind":"Type","span":{"file_name":[115,114,99,47,109,97,105,110,46,114,115],"byte_start":802,"byte_end":810,"line_start":42,"line_end":42,"column_start":23,"column_end":31},"ref_id":{"krate":2,"index":44730}},{"kind":"Variable","span":{"file_name":[115,114,99,47,109,97,105,110,46,114,115],"byte_start":835,"byte_end":838,"line_start":43,"line_end":43,"column_start":9,"column_end":12},"ref_id":{"krate":0,"index":4294967164}},{"kind":"Variable","span":{"file_name":[115,114,99,47,109,97,105,110,46,114,115],"byte_start":909,"byte_end":918,"line_start":48,"line_end":48,"column_start":8,"column_end":17},"ref_id":{"krate":0,"index":4294967179}},{"kind":"Function","span":{"file_name":[115,114,99,47,109,97,105,110,46,114,115],"byte_start":981,"byte_end":990,"line_start":49,"line_end":49,"column_start":56,"column_end":65},"ref_id":{"krate":0,"index":16}},{"kind":"Variable","span":{"file_name":[115,114,99,47,109,97,105,110,46,114,115],"byte_start":959,"byte_end":980,"line_start":49,"line_end":49,"column_start":34,"column_end":55},"ref_id":{"krate":0,"index":4294967169}},{"kind":"Variable","span":{"file_name":[115,114,99,47,109,97,105,110,46,114,115],"byte_start":991,"byte_end":1000,"line_start":49,"line_end":49,"column_start":66,"column_end":75},"ref_id":{"krate":0,"index":4294967179}},{"kind":"Function","span":{"file_name":[115,114,99,47,109,97,105,110,46,114,115],"byte_start":1060,"byte_end":1069,"line_start":50,"line_end":50,"column_start":57,"column_end":66},"ref_id":{"krate":0,"index":16}},{"kind":"Variable","span":{"file_name":[115,114,99,47,109,97,105,110,46,114,115],"byte_start":1038,"byte_end":1059,"line_start":50,"line_end":50,"column_start":35,"column_end":56},"ref_id":{"krate":0,"index":4294967169}},{"kind":"Variable","span":{"file_name":[115,114,99,47,109,97,105,110,46,114,115],"byte_start":1107,"byte_end":1117,"line_start":56,"line_end":56,"column_start":12,"column_end":22},"ref_id":{"krate":0,"index":4294967175}},{"kind":"Function","span":{"file_name":[115,114,99,47,109,97,105,110,46,114,115],"byte_start":1244,"byte_end":1253,"line_start":61,"line_end":61,"column_start":59,"column_end":68},"ref_id":{"krate":0,"index":16}},{"kind":"Variable","span":{"file_name":[115,114,99,47,109,97,105,110,46,114,115],"byte_start":1222,"byte_end":1243,"line_start":61,"line_end":61,"column_start":37,"column_end":58},"ref_id":{"krate":0,"index":4294967169}},{"kind":"Variable","span":{"file_name":[115,114,99,47,109,97,105,110,46,114,115],"byte_start":1254,"byte_end":1263,"line_start":61,"line_end":61,"column_start":69,"column_end":78},"ref_id":{"krate":0,"index":4294967179}},{"kind":"Function","span":{"file_name":[115,114,99,47,109,97,105,110,46,114,115],"byte_start":1302,"byte_end":1322,"line_start":67,"line_end":67,"column_start":5,"column_end":25},"ref_id":{"krate":0,"index":18}}],"macro_refs":[],"relations":[{"span":{"file_name":[115,114,99,47,109,97,105,110,46,114,115],"byte_start":147,"byte_end":153,"line_start":12,"line_end":12,"column_start":10,"column_end":16},"kind":{"variant":"Impl","fields":[0]},"from":{"krate":0,"index":10},"to":{"krate":4294967295,"index":4294967295}}]}